{
    "js": [
        "js/dataTables.fixedColumns.js",
        "js/dataTables.fixedColumns.min.js",
        "js/FixedColumns.js",
        "js/index.js",
        "js/dataTables.fixedColumns.min.mjs",
        "js/dataTables.fixedColumns.mjs"
    ],
    "css": [],
    "types": [
        "types/FixedColumns.d.ts",
        "types/index.d.ts",
        "types/types.d.ts"
    ],
    "src-repo": "http://github.com/DataTables/FixedColumns",
    "last-tag": "5.0.4",
    "last-sync": "ef7fdd9a3f526d8420ebe87d1a19aab578f7a546"
}