{
    "js": [
        "js/dataTables.fixedColumns.js",
        "js/dataTables.fixedColumns.min.js",
        "js/FixedColumns.js",
        "js/index.js",
        "js/dataTables.fixedColumns.min.mjs",
        "js/dataTables.fixedColumns.mjs"
    ],
    "css": [],
    "types": [
        "types/FixedColumns.d.ts",
        "types/index.d.ts",
        "types/types.d.ts"
    ],
    "src-repo": "http://github.com/DataTables/FixedColumns",
    "last-tag": "4.3.0",
    "last-sync": "b71bf6a193c7315748d4cb14c245f6ec5265a8e2"
}